Workbook

Sheet README
A1: Center for People — Financial Dashboard
A2: FY2026 Board of Directors Reporting Package • YTD as of April 30, 2026
A4: Contents
A5: Tab | B5: Purpose
A6: Dashboard | B6: One-page executive summary — KPI tiles, budget vs actual snapshot, monthly trend, top/bottom projects.
A7: Cash | B7: Cash position, liquidity (months of cash), and benchmark context.
A8: Revenue & Expenses | B8: YTD totals (incl. and excl. in-kind), revenue by category, expense by category.
A9: Budget vs Actual | B9: Full YTD budget vs actual by category with variance $/% and Favorable/Unfavorable status.
A10: Project Profitability | B10: All projects ranked by net surplus/(deficit) YTD with monthly detail.
A11: Monthly | B11: Monthly P&L trend, cumulative net income, and monthly net vs budget.
A12: Balance Sheet | B12: Full April 30, 2026 balance sheet from source GL.
A15: Source Data
A16: • Income Statement: Blackbaud Financial Edge NXT — Income Statement (Period: 04/30/2026 YTD)
A17: • Balance Sheet: Blackbaud Financial Edge NXT — Balance Sheet (As of 04/30/2026)
A18: • Project Detail: Blackbaud Financial Edge NXT — P&L Project Detail (Periods Jan–Apr 2026)
A19: • Budget: FE_2026OPERBudget KM Import 3-18-26.xlsx (OPER-2026 scenario, monthly periods)

Sheet Dashboard
A1: Center for People | Board Financial Dashboard
A2: YTD as of April 30, 2026 • FY2026 (Calendar Year) • Prepared by: Karin Micek, Treasurer
A4: Key Performance Indicators (YTD through April 30)
A6: CASH ON HAND | E6: YTD TOTAL REVENUE | I6: YTD TOTAL EXPENSES | M6: YTD NET INCOME
A7: =Cash!B8 -> 988292.85 | E7: ='Revenue & Expenses'!B5 -> 1831397 | I7: ='Revenue & Expenses'!B6 -> 1891274.8 | M7: ='Revenue & Expenses'!B7 -> -59877.81
A9: Operating + Savings (STFIT) | E9: Cash + In-Kind (Jan–Apr) | I9: Cash + In-Kind (Jan–Apr) | M9: Surplus / (Deficit)
A11: MONTHS OF CASH | E11: PROFITABLE PROJECTS | I11: CASH REVENUE YTD | M11: CASH EXPENSES YTD
A12: =Cash!B12 -> 5.1198895 | E12: ='Project Profitability'!H2 -> 0.30136986 | I12: ='Revenue & Expenses'!B12 -> 712242.65 | M12: ='Revenue & Expenses'!B13 -> 772120.46
A14: Liquidity runway @ cash burn | E14: % of projects net-positive YTD | I14: Excludes in-kind contributions | M14: Excludes in-kind expenses
A16: Budget vs Actual — YTD Summary
A18: Metric | D18: YTD Budget | G18: YTD Actual | J18: Variance $ | M18: Variance % | P18: Status
A19: Revenue | D19: ='Budget vs Actual'!B5 -> 991426.31 | G19: ='Revenue & Expenses'!B5 -> 1831397 | J19: =G19-D19 -> 839970.68 | M19: =IFERROR((G19-D19)/ABS(D19),0) -> 0.84723461 | P19: =IF(J19>=0,"Favorable","Unfavorable") -> Favorable
A20: Expenses | D20: ='Budget vs Actual'!B6 -> 1248465.5 | G20: ='Revenue & Expenses'!B6 -> 1891274.8 | J20: =G20-D20 -> 642809.26 | M20: =IFERROR((G20-D20)/ABS(D20),0) -> 0.51487946 | P20: =IF(J20<=0,"Favorable","Unfavorable") -> Unfavorable
A21: Net Income | D21: ='Budget vs Actual'!B7 -> -257039.23 | G21: ='Revenue & Expenses'!B7 -> -59877.81 | J21: =G21-D21 -> 197161.42 | M21: =IFERROR((G21-D21)/ABS(D21),0) -> 0.76704797 | P21: =IF(J21>=0,"Favorable","Unfavorable") -> Favorable
A23: Monthly Net Income Trend — FY2026
A25: Month | B25: Revenue | C25: Expenses | D25: Net Income
A26: Jan 2026 | B26: =Monthly!B5 -> 493453.89 | C26: =Monthly!C5 -> 438952.61 | D26: =Monthly!D5 -> 54501.28
A27: Feb 2026 | B27: =Monthly!B6 -> 411401.94 | C27: =Monthly!C6 -> 456590.7 | D27: =Monthly!D6 -> -45188.76
A28: Mar 2026 | B28: =Monthly!B7 -> 484329.85 | C28: =Monthly!C7 -> 527892.92 | D28: =Monthly!D7 -> -43563.07
A29: Apr 2026 | B29: =Monthly!B8 -> 442211.31 | C29: =Monthly!C8 -> 467977.99 | D29: =Monthly!D8 -> -25766.68
A43: Project Profitability — Top 5 Surplus & Top 5 Deficit
A45: TOP 5 SURPLUS PROJECTS | I45: TOP 5 DEFICIT PROJECTS
A46: Project | F46: Net Surplus | I46: Project | N46: Net Deficit
A47: [2024] Acklie | F47: 50000 | I47: [8888] General Project | N47: -233950.99
A48: [3005] One-time | F48: 49632.6 | I48: [2015] DOJ SCA | N48: -52509.98
A49: [4018] Battle of the Bartenders | F49: 42826.89 | I49: [2001a] VLS 7/24 - 6/25 | N49: -47204.93
A50: [2019] POP | F50: 41620.27 | I50: [5004] Nutrition Equity | N50: -31572.3
A51: [3007] Donor-Advised Funds | F51: 30059.86 | I51: [4004] Give to Lincoln Day | N51: -10735.14
A53: Note: General Project [8888] captures non-allocated administrative/overhead expense; the deficit there is funded by unrestricted gifts (a normal pattern for non-profits, not a red flag).

Sheet Cash
A1: Cash Position — As of April 30, 2026
A3: Cash & Cash Equivalents
A5: Union Bank Checking (Operating) | B5: 64099.42
A6: STFIT Savings Account | B6: 924193.43
A7: Total Cash & Cash Equivalents | B7: =SUM(B5:B6) -> 988292.85
A8: Cash on Hand (KPI helper) | B8: =B7 -> 988292.85
A10: Liquidity Analysis
A11: YTD Cash Expenses (4 months) | B11: ='Revenue & Expenses'!B13 -> 772120.46
A12: Months of Cash on Hand | B12: =B7/(B11/4) -> 5.1198895
A13: Avg Monthly Cash Burn | B13: =B11/4 -> 193030.11
A15: Benchmark Context
A16: Industry guideline: 3–6 months of operating cash is considered healthy for non-profits; 6+ months is strong.

Sheet Revenue & Expenses
A1: Revenue & Expenses Summary — YTD April 2026
A3: Headline Totals
A4: Metric | B4: YTD Total
A5: Total Revenue (incl. In-Kind) | B5: 1831397
A6: Total Expenses (incl. In-Kind) | B6: 1891274.8
A7: NET INCOME / (LOSS) | B7: =B5-B6 -> -59877.81
A9: Excluding In-Kind (Cash Basis)
A11: Total In-Kind (Revenue & Expense, offsetting) | B11: 1119154.3
A12: Cash Revenue YTD | B12: =B5-B11 -> 712242.65
A13: Cash Expenses YTD | B13: =B6-1119154.34 -> 772120.46
A14: Cash Net Income YTD | B14: =B12-B13 -> -59877.81
A16: Revenue by Category (YTD)
A17: Category | B17: YTD Actual | C17: % of Total
A18: In-Kind Contributions | B18: 1119154.3 | C18: =IFERROR(B18/$B$27,0) -> 0.61109325
A19: Grants | B19: 482965.14 | C19: =IFERROR(B19/$B$27,0) -> 0.26371406
A20: Contributions - Unrestricted | B20: 188966.2 | C20: =IFERROR(B20/$B$27,0) -> 0.10318145
A21: Rent Income | B21: 18398 | C21: =IFERROR(B21/$B$27,0) -> 0.010045883
A22: Interest Income | B22: 10361.6 | C22: =IFERROR(B22/$B$27,0) -> 0.0056577575
A23: Earned Mission Revenue | B23: 7380 | C23: =IFERROR(B23/$B$27,0) -> 0.0040297107
A24: Contributions - Restricted | B24: 1971.21 | C24: =IFERROR(B24/$B$27,0) -> 0.0010763423
A25: Miscellaneous Income | B25: 1535 | C25: =IFERROR(B25/$B$27,0) -> 0.00083815798
A26: Other Income | B26: 665.5 | C26: =IFERROR(B26/$B$27,0) -> 0.0003633838
A27: Total Revenue | B27: =SUM(B18:B26) -> 1831397 | C27: 1
A29: Expenses by Category (YTD)
A30: Category | B30: YTD Actual | C30: % of Total
A31: In-Kind Expenses | B31: 1119154.3 | C31: =IFERROR(B31/$B$58,0) -> 0.59174602
A32: Salaries | B32: 378502.95 | C32: =IFERROR(B32/$B$58,0) -> 0.20013112
A33: Depreciation | B33: 60542.67 | C33: =IFERROR(B33/$B$58,0) -> 0.032011567
A34: Supplies | B34: 54971.12 | C34: =IFERROR(B34/$B$58,0) -> 0.029065644
A35: Professional Fees | B35: 52338.24 | C35: =IFERROR(B35/$B$58,0) -> 0.027673525
A36: Building/Grounds | B36: 49274.35 | C36: =IFERROR(B36/$B$58,0) -> 0.026053512
A37: Insurance | B37: 29864.91 | C37: =IFERROR(B37/$B$58,0) -> 0.015790889
A38: Payroll Tax | B38: 28500.61 | C38: =IFERROR(B38/$B$58,0) -> 0.015069523
A39: Computer/Software | B39: 26774.68 | C39: =IFERROR(B39/$B$58,0) -> 0.014156949
A40: Phone/Utilities | B40: 18462.71 | C40: =IFERROR(B40/$B$58,0) -> 0.0097620452
A41: Group Insurance | B41: 17827.85 | C41: =IFERROR(B41/$B$58,0) -> 0.0094263668
A42: Accounting Fees | B42: 15000 | C42: =IFERROR(B42/$B$58,0) -> 0.0079311584
... A57: Employee Benefits | B57: -220 | C57: =IFERROR(B57/$B$58,0) -> -0.00011632366
A58: Total Expenses | B58: =SUM(B31:B57) -> 1891274.8 | C58: 1

Sheet Budget vs Actual
A1: YTD Budget vs Actual — FY2026 (Jan–Apr)
A3: Headline Totals
A4: Metric | B4: YTD Budget | C4: YTD Actual | D4: Variance $ | E4: Variance % | F4: Status | G4: Annual Budget | H4: YTD % of Year
A5: Revenue | B5: 991426.31 | C5: ='Revenue & Expenses'!B5 -> 1831397 | D5: =C5-B5 -> 839970.68 | E5: =IFERROR((C5-B5)/ABS(B5),0) -> 0.84723461 | F5: =IF(D5>=0,"Favorable","Unfavorable") -> Favorable | G5: 3642540.1 | H5: =IFERROR(C5/G5,0) -> 0.50278019
A6: Expenses | B6: 1248465.5 | C6: ='Revenue & Expenses'!B6 -> 1891274.8 | D6: =C6-B6 -> 642809.26 | E6: =IFERROR((C6-B6)/ABS(B6),0) -> 0.51487946 | F6: =IF(D6<=0,"Favorable","Unfavorable") -> Unfavorable | G6: 3796862.3 | H6: =IFERROR(C6/G6,0) -> 0.49811519
A7: Net Income / (Loss) | B7: =B5-B6 -> -257039.23 | C7: ='Revenue & Expenses'!B7 -> -59877.81 | D7: =C7-B7 -> 197161.42 | E7: =IFERROR((C7-B7)/ABS(B7),0) -> 0.76704797 | F7: =IF(D7>=0,"Favorable","Unfavorable") -> Favorable | G7: =G5-G6 -> -154322.25 | H7: =IFERROR(C7/G7,0) -> 0.38800503
A9: Revenue Detail — by Category
A10: Category | B10: YTD Budget | C10: YTD Actual | D10: Variance $ | E10: Variance % | F10: Status | G10: Annual Budget | H10: YTD %
A11: Grants | B11: 674800.11 | C11: 482965.14 | D11: =C11-B11 -> -191834.97 | E11: =IFERROR((C11-B11)/ABS(B11),IF(C11<>0,1,0)) -> -0.28428414 | F11: =IF(D11>=0,"Favorable","Unfavorable") -> Unfavorable | G11: 1680911 | H11: =IFERROR(C11/G11,0) -> 0.28732345
A12: In-Kind Contributions | B12: 0 | C12: 1119154.3 | D12: =C12-B12 -> 1119154.3 | E12: =IFERROR((C12-B12)/ABS(B12),IF(C12<>0,1,0)) -> 1 | F12: =IF(D12>=0,"Favorable","Unfavorable") -> Favorable | G12: 0 | H12: =IFERROR(C12/G12,0) -> 0
A13: Contributions - Unrestricted | B13: 159594.92 | C13: 188966.2 | D13: =C13-B13 -> 29371.28 | E13: =IFERROR((C13-B13)/ABS(B13),IF(C13<>0,1,0)) -> 0.18403643 | F13: =IF(D13>=0,"Favorable","Unfavorable") -> Favorable | G13: 1372885.1 | H13: =IFERROR(C13/G13,0) -> 0.13764167
A14: Bequest/Endowment | B14: 100000 | C14: 0 | D14: =C14-B14 -> -100000 | E14: =IFERROR((C14-B14)/ABS(B14),IF(C14<>0,1,0)) -> -1 | F14: =IF(D14>=0,"Favorable","Unfavorable") -> Unfavorable | G14: 100000 | H14: =IFERROR(C14/G14,0) -> 0
A15: Rent Income | B15: 20581.32 | C15: 18398 | D15: =C15-B15 -> -2183.32 | E15: =IFERROR((C15-B15)/ABS(B15),IF(C15<>0,1,0)) -> -0.1060826 | F15: =IF(D15>=0,"Favorable","Unfavorable") -> Unfavorable | G15: 84244 | H15: =IFERROR(C15/G15,0) -> 0.21838944
A16: Earned Mission Revenue | B16: 20550 | C16: 7380 | D16: =C16-B16 -> -13170 | E16: =IFERROR((C16-B16)/ABS(B16),IF(C16<>0,1,0)) -> -0.64087591 | F16: =IF(D16>=0,"Favorable","Unfavorable") -> Unfavorable | G16: 80000 | H16: =IFERROR(C16/G16,0) -> 0.09225
A17: Interest Income | B17: 8333.32 | C17: 10361.6 | D17: =C17-B17 -> 2028.28 | E17: =IFERROR((C17-B17)/ABS(B17),IF(C17<>0,1,0)) -> 0.24339399 | F17: =IF(D17>=0,"Favorable","Unfavorable") -> Favorable | G17: 25000 | H17: =IFERROR(C17/G17,0) -> 0.414464
A18: Other Income | B18: 5900 | C18: 665.5 | D18: =C18-B18 -> -5234.5 | E18: =IFERROR((C18-B18)/ABS(B18),IF(C18<>0,1,0)) -> -0.88720339 | F18: =IF(D18>=0,"Favorable","Unfavorable") -> Unfavorable | G18: 180000 | H18: =IFERROR(C18/G18,0) -> 0.0036972222
A19: Contributions - Restricted | B19: 1666.64 | C19: 1971.21 | D19: =C19-B19 -> 304.57 | E19: =IFERROR((C19-B19)/ABS(B19),IF(C19<>0,1,0)) -> 0.18274492 | F19: =IF(D19>=0,"Favorable","Unfavorable") -> Favorable | G19: 5000 | H19: =IFERROR(C19/G19,0) -> 0.394242
A20: Miscellaneous Income | B20: 0 | C20: 1535 | D20: =C20-B20 -> 1535 | E20: =IFERROR((C20-B20)/ABS(B20),IF(C20<>0,1,0)) -> 1 | F20: =IF(D20>=0,"Favorable","Unfavorable") -> Favorable | G20: 0 | H20: =IFERROR(C20/G20,0) -> 0
A21: Total Revenue | B21: =SUM(B11:B20) -> 991426.31 | C21: =SUM(C11:C20) -> 1831397 | D21: =C21-B21 -> 839970.68 | E21: =IFERROR((C21-B21)/ABS(B21),0) -> 0.84723461 | G21: =SUM(G11:G20) -> 3528040.1 | H21: =IFERROR(C21/G21,0) -> 0.51909756
A23: Expense Detail — by Category
A24: Category | B24: YTD Budget | C24: YTD Actual | D24: Variance $ | E24: Variance % | F24: Status | G24: Annual Budget | H24: YTD %
A25: In-Kind Expenses | B25: 0 | C25: 1119154.3 | D25: =C25-B25 -> 1119154.3 | E25: =IFERROR((C25-B25)/ABS(B25),IF(C25<>0,1,0)) -> 1 | F25: =IF(D25<=0,"Favorable","Unfavorable") -> Unfavorable | G25: 0 | H25: =IFERROR(C25/G25,0) -> 0
A26: Salaries | B26: 584093 | C26: 378502.95 | D26: =C26-B26 -> -205590.05 | E26: =IFERROR((C26-B26)/ABS(B26),IF(C26<>0,1,0)) -> -0.3519817 | F26: =IF(D26<=0,"Favorable","Unfavorable") -> Favorable | G26: 1752279 | H26: =IFERROR(C26/G26,0) -> 0.2160061
A27: Supplies | B27: 208029.9 | C27: 54971.12 | D27: =C27-B27 -> -153058.78 | E27: =IFERROR((C27-B27)/ABS(B27),IF(C27<>0,1,0)) -> -0.73575375 | F27: =IF(D27<=0,"Favorable","Unfavorable") -> Favorable | G27: 635271.5 | H27: =IFERROR(C27/G27,0) -> 0.086531696
A28: Depreciation | B28: 60000 | C28: 60542.67 | D28: =C28-B28 -> 542.67 | E28: =IFERROR((C28-B28)/ABS(B28),IF(C28<>0,1,0)) -> 0.0090445 | F28: =IF(D28<=0,"Favorable","Unfavorable") -> Unfavorable | G28: 180000 | H28: =IFERROR(C28/G28,0) -> 0.33634817
A29: Group Insurance | B29: 99311.28 | C29: 17827.85 | D29: =C29-B29 -> -81483.43 | E29: =IFERROR((C29-B29)/ABS(B29),IF(C29<>0,1,0)) -> -0.82048515 | F29: =IF(D29<=0,"Favorable","Unfavorable") -> Favorable | G29: 297933.94 | H29: =IFERROR(C29/G29,0) -> 0.059838265
A30: Professional Fees | B30: 44658 | C30: 52338.24 | D30: =C30-B30 -> 7680.24 | E30: =IFERROR((C30-B30)/ABS(B30),IF(C30<>0,1,0)) -> 0.17197904 | F30: =IF(D30<=0,"Favorable","Unfavorable") -> Unfavorable | G30: 110724 | H30: =IFERROR(C30/G30,0) -> 0.47269102
A31: Phone/Utilities | B31: 58688.2 | C31: 18462.71 | D31: =C31-B31 -> -40225.49 | E31: =IFERROR((C31-B31)/ABS(B31),IF(C31<>0,1,0)) -> -0.68541018 | F31: =IF(D31<=0,"Favorable","Unfavorable") -> Favorable | G31: 176064.66 | H31: =IFERROR(C31/G31,0) -> 0.10486324
A32: Payroll Tax | B32: 46727.44 | C32: 28500.61 | D32: =C32-B32 -> -18226.83 | E32: =IFERROR((C32-B32)/ABS(B32),IF(C32<>0,1,0)) -> -0.39006695 | F32: =IF(D32<=0,"Favorable","Unfavorable") -> Favorable | G32: 140182.32 | H32: =IFERROR(C32/G32,0) -> 0.20331102
A33: Insurance | B33: 36666.67 | C33: 29864.91 | D33: =C33-B33 -> -6801.76 | E33: =IFERROR((C33-B33)/ABS(B33),IF(C33<>0,1,0)) -> -0.18550253 | F33: =IF(D33<=0,"Favorable","Unfavorable") -> Favorable | G33: 110000 | H33: =IFERROR(C33/G33,0) -> 0.27149918
A34: Building/Grounds | B34: 0 | C34: 49274.35 | D34: =C34-B34 -> 49274.35 | E34: =IFERROR((C34-B34)/ABS(B34),IF(C34<>0,1,0)) -> 1 | F34: =IF(D34<=0,"Favorable","Unfavorable") -> Unfavorable | G34: 0 | H34: =IFERROR(C34/G34,0) -> 0
A35: Computer/Software | B35: 15581.33 | C35: 26774.68 | D35: =C35-B35 -> 11193.35 | E35: =IFERROR((C35-B35)/ABS(B35),IF(C35<>0,1,0)) -> 0.71838219 | F35: =IF(D35<=0,"Favorable","Unfavorable") -> Unfavorable | G35: 46744.05 | H35: =IFERROR(C35/G35,0) -> 0.57279333
A36: Repairs/Maintenance | B36: 26666.64 | C36: 10694.86 | D36: =C36-B36 -> -15971.78 | E36: =IFERROR((C36-B36)/ABS(B36),IF(C36<>0,1,0)) -> -0.59894235 | F36: =IF(D36<=0,"Favorable","Unfavorable") -> Favorable | G36: 80000 | H36: =IFERROR(C36/G36,0) -> 0.13368575
... A53: Employee Benefits | B53: 333.32 | C53: -220 | D53: =C53-B53 -> -553.32 | E53: =IFERROR((C53-B53)/ABS(B53),IF(C53<>0,1,0)) -> -1.6600264 | F53: =IF(D53<=0,"Favorable","Unfavorable") -> Favorable | G53: 1000 | H53: =IFERROR(C53/G53,0) -> -0.22
A54: Total Expenses | B54: =SUM(B25:B53) -> 1248465.5 | C54: =SUM(C25:C53) -> 1891274.8 | D54: =C54-B54 -> 642809.26 | E54: =IFERROR((C54-B54)/ABS(B54),0) -> 0.51487946 | G54: =SUM(G25:G53) -> 3796862.3 | H54: =IFERROR(C54/G54,0) -> 0.49811519
A56: Note: In-Kind contributions and expenses are not budgeted by the organization (a common non-profit practice). They appear in actuals only and offset to zero net impact. Largest "Unfavorable" expense variances on cash-budgeted lines should be the focus of board commentary; budget timing differences (e.g., $100K Bequest planned later in the year) may also drive variances.

Sheet Project Profitability
A1: Project Profitability Ratio — All Projects YTD
G2: % Profitable: | H2: =COUNTIF(E6:E78,">0")/COUNTA(E6:E78) -> 0.30136986
A4: Project Detail — Revenue, Expense, Net (YTD)
A5: Code | B5: Project Name | C5: Revenue | D5: Expense | E5: Net | F5: Margin % | G5: Jan | H5: Feb | I5: Mar | J5: Apr | K5: Rank
A6: 2024 | B6: Acklie | C6: 50000 | D6: 0 | E6: =C6-D6 -> 50000 | F6: =IFERROR(E6/C6,IF(D6>0,-1,0)) -> 1 | G6: 50000 | H6: 0 | I6: 0 | J6: 0 | K6: 1
A7: 3005 | B7: One-time | C7: 49632.6 | D7: 0 | E7: =C7-D7 -> 49632.6 | F7: =IFERROR(E7/C7,IF(D7>0,-1,0)) -> 1 | G7: 22651.63 | H7: 4452.49 | I7: 10643.25 | J7: 11885.23 | K7: 2
A8: 4018 | B8: Battle of the Bartenders | C8: 44500 | D8: 1673.11 | E8: =C8-D8 -> 42826.89 | F8: =IFERROR(E8/C8,IF(D8>0,-1,0)) -> 0.96240202 | G8: 0 | H8: 0 | I8: 17500 | J8: 25326.89 | K8: 3
A9: 2019 | B9: POP | C9: 50000 | D9: 8379.73 | E9: =C9-D9 -> 41620.27 | F9: =IFERROR(E9/C9,IF(D9>0,-1,0)) -> 0.8324054 | G9: 22939.27 | H9: -2108.98 | I9: -2104.13 | J9: 22894.11 | K9: 4
A10: 3007 | B10: Donor-Advised Funds | C10: 30059.86 | D10: 0 | E10: =C10-D10 -> 30059.86 | F10: =IFERROR(E10/C10,IF(D10>0,-1,0)) -> 1 | G10: 16950 | H10: 0 | I10: 10285.46 | J10: 2824.4 | K10: 5
A11: 4005 | B11: Q4 Campaign | C11: 29935 | D11: 0 | E11: =C11-D11 -> 29935 | F11: =IFERROR(E11/C11,IF(D11>0,-1,0)) -> 1 | G11: 25640 | H11: 0 | I11: 4295 | J11: 0 | K11: 6
A12: 2025a | B12: Abel Foundation 2025 | C12: 25000 | D12: 0 | E12: =C12-D12 -> 25000 | F12: =IFERROR(E12/C12,IF(D12>0,-1,0)) -> 1 | G12: 25000 | H12: 0 | I12: 0 | J12: 0 | K12: 7
A13: 2001 | B13: VLS | C13: 151604.95 | D13: 127986.26 | E13: =C13-D13 -> 23618.69 | F13: =IFERROR(E13/C13,IF(D13>0,-1,0)) -> 0.15579102 | G13: 34376.11 | H13: -999.92 | I13: -6735.06 | J13: -3022.44 | K13: 8
A14: 5009 | B14: SCC Rental | C14: 17273 | D14: 1063.45 | E14: =C14-D14 -> 16209.55 | F14: =IFERROR(E14/C14,IF(D14>0,-1,0)) -> 0.93843281 | G14: 4090.19 | H14: 4186.18 | I14: 3923.97 | J14: 4009.21 | K14: 9
A15: 3009 | B15: Workplace Giving | C15: 12506.96 | D15: 0 | E15: =C15-D15 -> 12506.96 | F15: =IFERROR(E15/C15,IF(D15>0,-1,0)) -> 1 | G15: 7670.58 | H15: 0 | I15: 247.1 | J15: 4589.28 | K15: 10
A16: 3008 | B16: Stocks/Mutual Funds | C16: 11732.68 | D16: 0 | E16: =C16-D16 -> 11732.68 | F16: =IFERROR(E16/C16,IF(D16>0,-1,0)) -> 1 | G16: 100 | H16: 0 | I16: 2200 | J16: 9432.68 | K16: 11
A17: 2006 | B17: United Way : Nutrition Equity | C17: 11166.68 | D17: 0 | E17: =C17-D17 -> 11166.68 | F17: =IFERROR(E17/C17,IF(D17>0,-1,0)) -> 1 | G17: 2791.67 | H17: 2791.67 | I17: 2791.67 | J17: 2791.67 | K17: 12
... A78: 8888 | B78: General Project | C78: 122689.63 | D78: 356640.62 | E78: =C78-D78 -> -233950.99 | F78: =IFERROR(E78/C78,IF(D78>0,-1,0)) -> -1.9068522 | G78: -91734.63 | H78: 9894.93 | I78: -62271.61 | J78: -89839.68 | K78: 73
B79: TOTAL — ALL PROJECTS | C79: =SUM(C6:C78) -> 1831397 | D79: =SUM(D6:D78) -> 1891414.2 | E79: =SUM(E6:E78) -> -60017.23 | F79: =IFERROR(E79/C79,0) -> -0.032771284 | G79: =SUM(G6:G78) -> 54501.28 | H79: =SUM(H6:H78) -> -45188.76 | I79: =SUM(I6:I78) -> -43563.07 | J79: =SUM(J6:J78) -> -25766.68

Sheet Monthly
A1: Monthly P&L Trend — FY2026
A3: Monthly Performance
A4: Month | B4: Revenue | C4: Expenses | D4: Net Income | E4: Budget Net | F4: Variance vs Budget | G4: Cumulative Net
A5: January 2026 | B5: 493453.89 | C5: 438952.61 | D5: =B5-C5 -> 54501.28 | E5: 107789.52 | F5: =D5-E5 -> -53288.24 | G5: =D5 -> 54501.28
A6: February 2026 | B6: 411401.94 | C6: 456590.7 | D6: =B6-C6 -> -45188.76 | E6: -169800.99 | F6: =D6-E6 -> 124612.23 | G6: =G5+D6 -> 9312.52
A7: March 2026 | B7: 484329.85 | C7: 527892.92 | D7: =B7-C7 -> -43563.07 | E7: -157426.37 | F7: =D7-E7 -> 113863.3 | G7: =G6+D7 -> -34250.55
A8: April 2026 | B8: 442211.31 | C8: 467977.99 | D8: =B8-C8 -> -25766.68 | E8: -97601.39 | F8: =D8-E8 -> 71834.71 | G8: =G7+D8 -> -60017.23
A9: YTD Total (Jan–Apr) | B9: =SUM(B5:B8) -> 1831397 | C9: =SUM(C5:C8) -> 1891414.2 | D9: =SUM(D5:D8) -> -60017.23 | E9: =SUM(E5:E8) -> -317039.23 | F9: =SUM(F5:F8) -> 257022 | G9: =G8 -> -60017.23

Sheet Balance Sheet
A1: Balance Sheet — As of April 30, 2026
A3: Assets
A4: 10100-00-1 | B4: Union Bank Checking | C4: 64099.42
A5: 10400-00-1 | B5: Savings (STFIT) Account | C5: 924193.43
A6: 11000-00-1 | B6: Accounts Receivable | C6: 21130
A7: 11100-00-1 | B7: Grants Receivable | C7: 139117.27
A8: 11200-00-1 | B8: Rent Receivables | C8: 475
A9: 11400-00-1 | B9: Other Receivables | C9: 0
A10: 12001-00-1 | B10: Inventory : Food | C10: 48129.6
A11: 12002-00-1 | B11: Inventory - Distribution | C11: 0
A12: 12003-00-1 | B12: Inventory - Diapers (Purchase) | C12: 0
A13: 12004-00-1 | B13: Inventory - Diapers (Donation) | C13: 0
A14: 14000-00-1 | B14: Prepaid Expenses | C14: 110047.94
A15: 15003-00-1 | B15: Equipment | C15: 563734.07
... A28: 19999-00-2 | B28: Due to/from Other Funds | C28: -2168464.1
B29: Total Assets | C29: =SUM(C4:C28) -> 4632958.5
A31: Liabilities
A32: 20000-00-1 | B32: Accounts Payable | C32: 31983.51
A33: 20001-00-1 | B33: Accounts Payable Clearing | C33: 0
A34: 20002-00-1 | B34: Credit Card - Union Bank | C34: 58224.84
A35: 21000-00-1 | B35: Credit Card Clearing account | C35: 0
A36: 23000-00-1 | B36: Accrued Expenses | C36: 37641.16
A37: 23100-00-1 | B37: Deferred Grant Income | C37: 0
A38: 23103-00-1 | B38: Deferred Rent Income | C38: 0
A39: 23200-00-1 | B39: Wages Payable | C39: 35376.26
A40: 23300-00-1 | B40: FICA Med Payable | C40: 2626.2
A41: 23600-00-1 | B41: State Payroll Taxes Payable | C41: 0
A42: 23750-00-1 | B42: Garnishments | C42: 0
A43: 23751-00-1 | B43: United Way Payable | C43: 0
... A53: 25050-00-1 | B53: Current portion of Lease Liab | C53: 10857.06
B54: Total Liabilities | C54: =SUM(C32:C53) -> 253718.76
A56: Net Assets
A57: 39005-00-1 | B57: Unrestricted Net Assets | C57: 6547703.8
A58: 39007-00-2 | B58: Temporarily Restricted Net Assets | C58: -2168464.1
B59: Total Net Assets | C59: =SUM(C57:C58) -> 4379239.7
B61: Total Liabilities + Net Assets | C61: =C54+C59 -> 4632958.5
